build_wheel_metadata.py
build_wheel_metadata-0.0.1.dist-info/METADATA
build_wheel_metadata-0.0.1.dist-info/WHEEL
build_wheel_metadata-0.0.1.dist-info/RECORD
