Metadata-Version: 2.4
Name: build-wheel-metadata
Version: 0.0.1
Summary: Module to prepare a python package distribution metadata.
Project-URL: Repository, https://github.com/dhiahmila/build-wheel-metadata
Project-URL: Issues, https://github.com/dhiahmila/build-wheel-metadata/issues
Author: Dhia Hmila
License: MIT License
Classifier: Intended Audience :: Developers
Classifier: License :: OSI Approved :: MIT License
Classifier: Programming Language :: Python :: 3
Classifier: Programming Language :: Python :: 3.9
Classifier: Programming Language :: Python :: 3.10
Classifier: Programming Language :: Python :: 3.11
Classifier: Programming Language :: Python :: 3.12
Classifier: Programming Language :: Python :: 3.13
Requires-Python: >=3.9
Requires-Dist: build>=1.2.0
